opentable_client/__init__.py
opentable_client/api/__init__.py
opentable_client/api/default/__init__.py
opentable_client/api/default/add_credit_card_cards_post.py
opentable_client/api/default/book_reservation_endpoint_book_post.py
opentable_client/api/default/cancel_reservation_reservations_confirmation_number_delete.py
opentable_client/api/default/get_current_user_info_auth_me_get.py
opentable_client/api/default/get_reservations_reservations_get.py
opentable_client/api/default/get_restaurant_availability_availability_restaurant_id_get.py
opentable_client/api/default/get_restaurant_timeslots_timeslots_restaurant_id_get.py
opentable_client/api/default/health_check_health_get.py
opentable_client/api/default/list_credit_cards_cards_get.py
opentable_client/api/default/modify_reservation_endpoint_reservations_confirmation_number_modify_put.py
opentable_client/api/default/search_restaurants_search_post.py
opentable_client/api/production/__init__.py
opentable_client/api/production/register_user_production_auth_register_post.py
opentable_client/client.py
opentable_client/errors.py
opentable_client/models/__init__.py
opentable_client/models/booking_request.py
opentable_client/models/cancel_request.py
opentable_client/models/card_create.py
opentable_client/models/http_validation_error.py
opentable_client/models/modify_reservation_request.py
opentable_client/models/search_request.py
opentable_client/models/user_create.py
opentable_client/models/user_public.py
opentable_client/models/validation_error.py
opentable_client/py.typed
opentable_client/types.py
opentable_rest_client-1.0.1.dist-info/LICENSE
opentable_rest_client-1.0.1.dist-info/METADATA
opentable_rest_client-1.0.1.dist-info/WHEEL
opentable_rest_client-1.0.1.dist-info/RECORD
