Metadata-Version: 2.3
Name: opentable-rest-client
Version: 1.0.1
Summary: A Python client library for the OpenTable REST API - search, book, and manage restaurant reservations
License: MIT
Keywords: opentable,restaurant,reservations,api,booking
Author: wheelis
Author-email: noreply@github.com
Requires-Python: >=3.9,<4.0
Classifier: Development Status :: 4 - Beta
Classifier: Intended Audience :: Developers
Classifier: License :: OSI Approved :: MIT License
Classifier: Operating System :: OS Independent
Classifier: Programming Language :: Python :: 3
Classifier: Programming Language :: Python :: 3.9
Classifier: Programming Language :: Python :: 3.10
Classifier: Programming Language :: Python :: 3.11
Classifier: Programming Language :: Python :: 3.12
Classifier: Programming Language :: Python :: 3.13
Classifier: Topic :: Internet :: WWW/HTTP :: Dynamic Content
Classifier: Topic :: Software Development :: Libraries :: Python Modules
Requires-Dist: attrs (>=22.2.0)
Requires-Dist: httpx (>=0.23.0,<0.29.0)
Requires-Dist: python-dateutil (>=2.8.0,<3.0.0)
Project-URL: Documentation, https://github.com/wheelis/opentable_mcp/blob/main/python_client/README.md
Project-URL: Homepage, https://github.com/wheelis/opentable_mcp
Project-URL: Repository, https://github.com/wheelis/opentable_mcp
